hds_821pr/__init__.py
hds_821pr/ascii.py
hds_821pr/dicts.py
hds_821pr/hex.py
hds_821pr-0.0.1.dist-info/METADATA
hds_821pr-0.0.1.dist-info/RECORD
hds_821pr-0.0.1.dist-info/WHEEL
hds_821pr-0.0.1.dist-info/top_level.txt
hds_821pr-0.0.1.dist-info/zip-safe
