Metadata-Version: 2.1
Name: hds-821pr
Version: 0.0.1
Summary: Library to interface with HDS-821PR HDMI 2x1 Multi-Viewer Switch Seamless Switcher w/ PIP Function
Home-page: https://github.com/ragingcomputer/hds_821pr
Author: Raging Computer
Author-email: UNKNOWN
License: MIT
Download-URL: https://github.com/ragingcomputer/hds_821pr/archive/0.0.1.tar.gz
Platform: UNKNOWN
Requires-Dist: pyserial (==3.4)
